ros_lab/__init__.py
ros_lab/entry.py
ros_lab/lab_shell/__init__.py
ros_lab/lab_shell/lab_shell.py
ros_lab-0.0.0.dist-info/LICENSE
ros_lab-0.0.0.dist-info/METADATA
ros_lab-0.0.0.dist-info/WHEEL
ros_lab-0.0.0.dist-info/entry_points.txt
ros_lab-0.0.0.dist-info/top_level.txt
ros_lab-0.0.0.dist-info/zip-safe
ros_lab-0.0.0.dist-info/RECORD
