Metadata-Version: 2.1
Name: ros-lab
Version: 0.0.0
Summary: Docker-Based Robot Operating System Virtual Lab
Home-page: https://github.com/MuchenSun/ros-lab
Author: Muchen Sun
Author-email: sunmch15@foxmail.com
License: GPLv3
Keywords: ROS Docker
Platform: UNKNOWN
Requires-Dist: docker (>=3.4.0)
